sqlalchemybundle/SqlAlchemyBundle.py
sqlalchemybundle/SqlAlchemyBundleTest.py
sqlalchemybundle/_config/config.yaml
sqlalchemybundle/_config/config_test.yaml
sqlalchemybundle/command/connection_aware_command.py
sqlalchemybundle/engine/EngineFactory.py
sqlalchemybundle/engine/EngineFactoryInterface.py
sqlalchemybundle/engine/EngineFactoryResolver.py
sqlalchemybundle/engine/EngineLazy.py
sqlalchemybundle/entity/Base.py
sqlalchemybundle/entity/EntityList.py
sqlalchemybundle/mssql/MsSqlEngineFactory.py
sqlalchemybundle/mysql/MySqlEngineFactory.py
sqlalchemybundle/session/SessionFactory.py
sqlalchemybundle/session/SessionLazy.py
sqlalchemybundle/table/TableCreatorCommand.py
sqlalchemybundle/testing/DummyEngineFactory.py
sqlalchemybundle/utils/LazyObject.py
pyfony_sqlalchemy_bundle-1.0.1.dist-info/entry_points.txt
pyfony_sqlalchemy_bundle-1.0.1.dist-info/WHEEL
pyfony_sqlalchemy_bundle-1.0.1.dist-info/METADATA
pyfony_sqlalchemy_bundle-1.0.1.dist-info/RECORD
